{
  "_class": "symbolInstance",
  "booleanOperation": 0,
  "do_objectID": "F01E5B40-533A-4257-B107-5DB7DE416D1F",
  "exportOptions": {
    "_class": "exportOptions",
    "do_objectID": "F4F5B84A-D75F-4946-AC4B-F13510BF4A60",
    "exportFormats": [
    ],
    "includedLayerIds": [
    ],
    "layerOptions": 0,
    "shouldTrim": false
  },
  "frame": {
    "_class": "rect",
    "constrainProportions": false,
    "do_objectID": "074F7FBD-65E4-4C3C-940A-8327C05C5117",
    "height": 24,
    "width": 24,
    "x": 1426,
    "y": 460
  },
  "horizontalSpacing": 0,
  "isFixedToViewport": false,
  "isFlippedHorizontal": false,
  "isFlippedVertical": false,
  "isLocked": false,
  "isVisible": true,
  "layerListExpandedType": 0,
  "name": "navigation",
  "nameIsFixed": false,
  "overrideValues": [
  ],
  "resizingConstraint": 63,
  "resizingType": 0,
  "rotation": 0,
  "scale": 1,
  "shouldBreakMaskChain": false,
  "style": {
    "_class": "style",
    "do_objectID": "5B7938B2-8472-412D-8CC7-6C33705B6F47",
    "endMarkerType": 0,
    "miterLimit": 10,
    "startMarkerType": 0,
    "windingRule": 1
  },
  "symbolID": "7690CEEF-E916-40E1-8B41-C9DA3C3AB05F",
  "verticalSpacing": 0
}